XRD/__init__.py
XRD/main.py
XRD/Layout/__init__.py
XRD/Layout/create_button.py
XRD/Layout/main_window_att.py
XRD/Layout/settings.py
XRD/Layout/style.py
XRD/Layout/utils_button.py
XRD/Plot/__init__.py
XRD/Plot/frame_attributes.py
XRD/Plot/plot_functions.py
XRD/Plot/style_plot.py
XRD/Plot/utils.py
XRD/Processing/__init__.py
XRD/Processing/function_common.py
XRD/Processing/xrd.py
inpxrd-1.0.1.dist-info/licenses/LICENSE
inpxrd-1.0.1.dist-info/METADATA
inpxrd-1.0.1.dist-info/WHEEL
inpxrd-1.0.1.dist-info/entry_points.txt
inpxrd-1.0.1.dist-info/top_level.txt
inpxrd-1.0.1.dist-info/RECORD
