Metadata-Version: 2.4
Name: INPXRD
Version: 1.0.1
Summary: Package for XRD data processing and visualization
Author-email: Thibaut Meyer <thibaut.meyer3@gmail.com>
License-Expression: GPL-3.0-or-later
Project-URL: Homepage, https://github.com/thi-mey/XRD
Keywords: XRD,InP
Classifier: Programming Language :: Python :: 3
Classifier: Operating System :: OS Independent
Requires-Python: >=3.9
License-File: LICENSE
Requires-Dist: fitspy
Requires-Dist: matplotlib
Requires-Dist: pandas
Requires-Dist: Pillow
Requires-Dist: PyQt5==5.15.11
Requires-Dist: PyQt5_sip==12.17.0
Dynamic: license-file
